{
    "lcoalData":[
        {
            "id":"0",
            "provice":"江西",
            "cites":[
                {
                    "num":"0",
                    "city":"南昌",
                    "town":[
                        "安义县", "进贤县", "南昌市", "南昌县", "新建县"
                    ]
                },
                {
                    "num":"1",
                    "town":[
                        "崇仁县", "东乡县", "抚州市", "广昌县", "金溪县", "乐安县", "黎川县", "南城县", "南丰县", "宜黄县", "资溪县"
                    ]
                },
                {
                    "num":"2",
                    "city":"赣州",
                    "town":[
                        "安远县", "崇义县", "大余县", "定南县", "赣县", "赣州市", "会昌县", "龙南县", "南康市", "宁都县", "全 南县", "瑞金市", "上犹县", "石城县", "信丰县", "兴国县", "寻乌县", "于都县"
                    ]
                },

                {
                    "num":"3",
                    "city":"吉安",
                    "town":[
                        "安福县", "吉安市", "吉安县", "吉水县", "井冈山市", "遂川县", "泰和县", "万安县", "峡江县", "新干县", "永丰县", "永新县"
                    ]
                }
            ]
            
        },
        {
            "id":"1",
            "provice":"广东",
            "cites":[
                {
                    "num":"0",
                    "city":"潮州",
                    "town":[
                        "潮安县", "潮州市", "饶平县"
                    ]
                },
                {
                    "num":"1",
                    "city":"广州",
                    "town":[
                        "从化市", "广州市", "增城市"
                    ]
                },
                {
                    "num":"2",
                    "city":"河源",
                    "town":[
                        "东源县", "和平县", "河源市", "连平县", "龙川县", "紫金县"
                    ]
                },

                {
                    "num":"3",
                    "city":"惠州",
                    "town":[
                        "博罗县", "惠东县", "惠阳市", "惠州市", "龙门县"
                    ]
                }
            ]
            
        },
        {
            "id":"2",
            "provice":"湖北",
            "cites":[
                {
                    "num":"0",
                    "city":"武汉",
                    "town":[
                        "武汉市"
                    ]
                },
                {
                    "num":"1",
                    "city":"荆州",
                    "town":[
                        "荆门市", "京山县", "沙洋县", "钟祥市"
                    ]
                },
                {
                    "num":"2",
                    "city":"黄冈",
                    "town":[
                        "红安县", "黄冈市", "黄梅县", "罗田县", "麻城市", "团风县", "武穴市", "英山县", "蕲春县", "浠水县"
                    ]
                },

                {
                    "num":"3",
                    "city":"潜江",
                    "town":[
                        "荆门市", "京山县", "沙洋县", "钟祥市"
                    ]
                }
            ]
            
        }
    ]
}

